README.rst
setup.py
whistler/__init__.py
whistler/bot.py
whistler/log.py
whistler/scripts.py
whistler.egg-info/PKG-INFO
whistler.egg-info/SOURCES.txt
whistler.egg-info/dependency_links.txt
whistler.egg-info/entry_points.txt
whistler.egg-info/requires.txt
whistler.egg-info/top_level.txt
whistler/mixins/__init__.py
whistler/mixins/help.py
whistler/mixins/log.py
whistler/mixins/motd.py
whistler/mixins/poll.py
whistler/mixins/post.py
whistler/mixins/short.py
whistler/mixins/task.py
whistler/mixins/toy.py
whistler/storage/__init__.py