Metadata-Version: 1.1
Name: whistler
Version: 1.5.2
Summary: An extensible MUC bot for XMPP.
Home-page: http://github.com/ajdiaz/whistler
Author: Andres J. Diaz
Author-email: ajdiaz@connectical.com
License: UNKNOWN
Platform: UNKNOWN
Classifier: Development Status :: 4 - Beta
Classifier: Intended Audience :: Developers
Classifier: License :: OSI Approved :: GNU General Public License (GPL)
Classifier: Operating System :: OS Independent
Classifier: Programming Language :: Python
Classifier: Topic :: Communications :: Chat
